py_ocsf/__init__.py
py_ocsf/__main__.py
py_ocsf/py.typed
py_ocsf-0.0.1.dev1747067353.dist-info/licenses/LICENSE
py_ocsf-0.0.1.dev1747067353.dist-info/METADATA
py_ocsf-0.0.1.dev1747067353.dist-info/WHEEL
py_ocsf-0.0.1.dev1747067353.dist-info/entry_points.txt
py_ocsf-0.0.1.dev1747067353.dist-info/top_level.txt
py_ocsf-0.0.1.dev1747067353.dist-info/RECORD
