Metadata-Version: 2.4
Name: py-ocsf
Version: 0.0.1.dev1747067353
Summary: The Python OCSF Library
Author-email: River Studio <pypi@river-studio.net>
License: GNU GPLv3.0
Project-URL: Homepage, https://github.com/river-studio-net/PyOCSF
Project-URL: Repository, https://github.com/river-studio-net/PyOCSF
Project-URL: Documentation, https://PyOCSF.readthedocs.io
Project-URL: Changelog, https://github.com/river-studio-net/PyOCSF/releases
Classifier: Development Status :: 1 - Planning
Classifier: Programming Language :: Python :: 3
Classifier: Programming Language :: Python :: 3.9
Classifier: Programming Language :: Python :: 3.10
Classifier: Programming Language :: Python :: 3.11
Classifier: Programming Language :: Python :: 3.12
Classifier: Programming Language :: Python :: 3.13
Requires-Python: >=3.9
License-File: LICENSE
Requires-Dist: click>=8.0.0
Dynamic: license-file
